neutrophils_core/__init__.py
neutrophils_core/config/__init__.py
neutrophils_core/config/arg_parser.py
neutrophils_core/config/config_loader.py
neutrophils_core/loader/ImageDataGenerator2D.py
neutrophils_core/loader/ImageDataGenerator3D.py
neutrophils_core/loader/__init__.py
neutrophils_core/loader/augmentations_2d.py
neutrophils_core/loader/augmentations_3d.py
neutrophils_core/loader/cache_manager.py
neutrophils_core/loader/concurrent_loader.py
neutrophils_core/loader/contrastive_generator.py
neutrophils_core/loader/data_utils.py
neutrophils_core/loader/hierarchical_labels.py
neutrophils_core/loader/multi_output_utils.py
neutrophils_core/loader/optimized_image_data_generator_3d.py
neutrophils_core/metrics/__init__.py
neutrophils_core/metrics/callbacks.py
neutrophils_core/metrics/classification_metrics.py
neutrophils_core/metrics/contrastive_losses.py
neutrophils_core/metrics/loss_functions.py
neutrophils_core/metrics/tensorboard_utils.py
neutrophils_core/models/__init__.py
neutrophils_core/models/compilation_utils.py
neutrophils_core/models/dynamic_residual_scaling.py
neutrophils_core/models/feature_extractor.py
neutrophils_core/models/feature_extractor_3d.py
neutrophils_core/models/heads.py
neutrophils_core/models/hierarchical_model.py
neutrophils_core/models/model_loader.py
neutrophils_core/models/model_utils.py
neutrophils_core/models/predictor.py
neutrophils_core/models/simclr.py
neutrophils_core/models/unified_interface.py
neutrophils_core/preprocessing/__init__.py
neutrophils_core/preprocessing/projection.py
neutrophils_core/utils/__init__.py
neutrophils_core/utils/embedding_visualization.py
neutrophils_core/utils/gpu_utils.py
neutrophils_core/utils/memory_utils.py
neutrophils_core-0.1.1.dist-info/METADATA
neutrophils_core-0.1.1.dist-info/WHEEL
neutrophils_core-0.1.1.dist-info/top_level.txt
neutrophils_core-0.1.1.dist-info/RECORD
