Metadata-Version: 2.1
Name: neutrophils-core
Version: 0.1.1
Summary: Core library for neutrophils classification with unified 2D/3D model interface
Author: BPI Oxford
License: MIT
Project-URL: Homepage, https://github.com/bpi-oxford/Neutrophils-Classifier-App
Project-URL: Repository, https://github.com/bpi-oxford/Neutrophils-Classifier-App
Project-URL: Issues, https://github.com/bpi-oxford/Neutrophils-Classifier-App/issues
Classifier: Development Status :: 3 - Alpha
Classifier: Intended Audience :: Science/Research
Classifier: Operating System :: OS Independent
Classifier: Programming Language :: Python :: 3
Classifier: Programming Language :: Python :: 3.8
Classifier: Programming Language :: Python :: 3.9
Classifier: Programming Language :: Python :: 3.10
Classifier: Programming Language :: Python :: 3.11
Classifier: Topic :: Scientific/Engineering :: Artificial Intelligence
Classifier: Topic :: Scientific/Engineering :: Image Processing
Requires-Python: >=3.8
Requires-Dist: numpy>=1.26.4
Requires-Dist: pandas
Requires-Dist: matplotlib
Requires-Dist: scikit-learn
Requires-Dist: scikit-image
Requires-Dist: numba
Requires-Dist: tensorflow
Requires-Dist: SimpleITK
Requires-Dist: tifffile
Requires-Dist: aicsimageio
Requires-Dist: bioformats-jar
Requires-Dist: aicspylibczi
Requires-Dist: pyvista[all]>=0.43.3
Requires-Dist: toml
Requires-Dist: tqdm
Provides-Extra: dev
Requires-Dist: pytest>=6.0; extra == "dev"
Requires-Dist: pytest-cov>=2.0; extra == "dev"
Requires-Dist: black>=21.0; extra == "dev"
Requires-Dist: flake8>=3.8; extra == "dev"
